videostudio/__init__.py
videostudio/audio_analyzer.py
videostudio/canvas.py
videostudio/download_script.py
videostudio/elements.py
videostudio/export.py
videostudio/manipulators.py
videostudio/transitions.py
videostudio-0.1.4.dist-info/METADATA
videostudio-0.1.4.dist-info/WHEEL
videostudio-0.1.4.dist-info/top_level.txt
videostudio-0.1.4.dist-info/RECORD
