Metadata-Version: 2.1
Name: videostudio
Version: 0.1.4
Summary: videostudio is a versatile video and audio processing package designed for creating, editing, and managing multimedia content. It leverages popular libraries such as MoviePy, Pydub, NumPy, and Scipy to provide powerful tools for handling audio and video files.
Home-page: https://github.com/alphatrait/videostudio
Author: Contentify AI
Author-email: hi@contentify.app
Classifier: Programming Language :: Python :: 3
Classifier: License :: OSI Approved :: MIT License
Classifier: Operating System :: OS Independent
Requires-Python: >=3.6
Requires-Dist: moviepy
Requires-Dist: pydub
Requires-Dist: numpy
Requires-Dist: scipy
Requires-Dist: speechrecognition
Requires-Dist: Pillow
